jupyterlab_rtc_hub_settings/__init__.py
jupyterlab_rtc_hub_settings/_version.py
jupyterlab_rtc_hub_settings/handlers.py
jupyterlab_rtc_hub_settings/hub_sharing_settings.py
jupyterlab_rtc_hub_settings/labextension/build_log.json
jupyterlab_rtc_hub_settings/labextension/package.json
jupyterlab_rtc_hub_settings/labextension/static/lib_index_js.aa27acd2f9d9b6c528e8.js
jupyterlab_rtc_hub_settings/labextension/static/lib_index_js.aa27acd2f9d9b6c528e8.js.map
jupyterlab_rtc_hub_settings/labextension/static/remoteEntry.dbd4ea211fb5054b4222.js
jupyterlab_rtc_hub_settings/labextension/static/remoteEntry.dbd4ea211fb5054b4222.js.map
jupyterlab_rtc_hub_settings/labextension/static/style.js
jupyterlab_rtc_hub_settings/labextension/static/style_index_js.7485244b9e0aa271a38c.js
jupyterlab_rtc_hub_settings/labextension/static/style_index_js.7485244b9e0aa271a38c.js.map
jupyterlab_rtc_hub_settings-0.1.3.data/data/etc/jupyter/jupyter_notebook_config.d/jupyterlab_rtc_hub_settings.json
jupyterlab_rtc_hub_settings-0.1.3.data/data/etc/jupyter/jupyter_server_config.d/jupyterlab_rtc_hub_settings.json
jupyterlab_rtc_hub_settings-0.1.3.data/data/share/jupyter/labextensions/jupyterlab_rtc_hub_settings/build_log.json
jupyterlab_rtc_hub_settings-0.1.3.data/data/share/jupyter/labextensions/jupyterlab_rtc_hub_settings/install.json
jupyterlab_rtc_hub_settings-0.1.3.data/data/share/jupyter/labextensions/jupyterlab_rtc_hub_settings/package.json
jupyterlab_rtc_hub_settings-0.1.3.data/data/share/jupyter/labextensions/jupyterlab_rtc_hub_settings/static/lib_index_js.aa27acd2f9d9b6c528e8.js
jupyterlab_rtc_hub_settings-0.1.3.data/data/share/jupyter/labextensions/jupyterlab_rtc_hub_settings/static/lib_index_js.aa27acd2f9d9b6c528e8.js.map
jupyterlab_rtc_hub_settings-0.1.3.data/data/share/jupyter/labextensions/jupyterlab_rtc_hub_settings/static/remoteEntry.dbd4ea211fb5054b4222.js
jupyterlab_rtc_hub_settings-0.1.3.dist-info/LICENSE
jupyterlab_rtc_hub_settings-0.1.3.dist-info/METADATA
jupyterlab_rtc_hub_settings-0.1.3.dist-info/WHEEL
jupyterlab_rtc_hub_settings-0.1.3.dist-info/top_level.txt
jupyterlab_rtc_hub_settings-0.1.3.dist-info/RECORD
