Metadata-Version: 2.1
Name: jupyterlab-rtc-hub-settings
Version: 0.1.3
Summary: A JupyterLab extension to manage real time collaboration settings on JupyterHub
Home-page: https://github.com/LabShare/jupyterlab-extensions
Author: Konstantin Taletskiy
Author-email: konstantin.taletskiy@labshare.org
License: BSD-3-Clause
Keywords: Jupyter,JupyterLab,JupyterLab3
Platform: Linux
Platform: Mac OS X
Platform: Windows
Classifier: License :: OSI Approved :: BSD License
Classifier: Programming Language :: Python
Classifier: Programming Language :: Python :: 3
Classifier: Programming Language :: Python :: 3.6
Classifier: Programming Language :: Python :: 3.7
Classifier: Programming Language :: Python :: 3.8
Classifier: Programming Language :: Python :: 3.9
Classifier: Framework :: Jupyter
Requires-Python: >=3.6
License-File: LICENSE
Requires-Dist: jupyter-server <3,>=1.6
Requires-Dist: escapism
